outhook/script.py
outhook-0.0.1.dist-info/entry_points.txt
outhook-0.0.1.dist-info/METADATA
outhook-0.0.1.dist-info/WHEEL
outhook-0.0.1.dist-info/RECORD
