Metadata-Version: 2.3
Name: outhook
Version: 0.0.1
Summary: 
Author: KarisAya
Author-email: karisaya@foxmail.com
Requires-Python: >=3.10
Classifier: Programming Language :: Python :: 3
Classifier: Programming Language :: Python :: 3.10
Classifier: Programming Language :: Python :: 3.11
Classifier: Programming Language :: Python :: 3.12
Classifier: Programming Language :: Python :: 3.13
